PyMySQLProxyCursor-0.2.3.dist-info/DESCRIPTION.rst
PyMySQLProxyCursor-0.2.3.dist-info/METADATA
PyMySQLProxyCursor-0.2.3.dist-info/RECORD
PyMySQLProxyCursor-0.2.3.dist-info/WHEEL
PyMySQLProxyCursor-0.2.3.dist-info/metadata.json
PyMySQLProxyCursor-0.2.3.dist-info/top_level.txt
proxycursor/__init__.py
proxycursor/utils/__init__.py
proxycursor/utils/parser.py
