Metadata-Version: 2.0
Name: PyMySQLProxyCursor
Version: 0.2.3
Summary: Simple PyMySQL ProxyCursor
Home-page: https://github.com/DailyHotel/PyMySQLProxyCursor/
Author: Randy Yoon
Author-email: randy.yoon@dailyhotel.com
License: MIT
Platform: UNKNOWN
Classifier: Programming Language :: Python :: 2
Classifier: Programming Language :: Python :: 2.7
Classifier: Programming Language :: Python :: 3
Classifier: Programming Language :: Python :: 3.4
Classifier: Programming Language :: Python :: 3.5
Classifier: Programming Language :: Python :: 3.6
Classifier: Intended Audience :: Developers
Classifier: License :: OSI Approved :: MIT License
Classifier: Topic :: Database
Requires-Dist: PyMYSQL (>=0.7.9)
Requires-Dist: six (>=1.10.0)
Requires-Dist: sqlparse (>=0.2.3)
